binance_downloader/__init__.py
binance_downloader/__main__.py
binance_downloader/api.py
binance_downloader/binance_utils.py
binance_downloader/cli.py
binance_downloader/db.py
binance_downloader/util.py
binance_downloader-0.2.5.dist-info/entry_points.txt
binance_downloader-0.2.5.dist-info/LICENSE
binance_downloader-0.2.5.dist-info/WHEEL
binance_downloader-0.2.5.dist-info/METADATA
binance_downloader-0.2.5.dist-info/RECORD
