Metadata-Version: 2.1
Name: binance-downloader
Version: 0.2.5
Summary: CLI to download k-line (candlestick/OHLC) data from Binance API
Home-page: https://github.com/anson-vandoren/binance-downloader.git
License: MIT
Keywords: Binance,Cryptocurrency,Finance,Technical Analysis
Author: Anson VanDoren
Author-email: anson.vandoren@gmail.com
Requires-Python: >=3.6.1
Classifier: Development Status :: 4 - Beta
Classifier: Environment :: Console
Classifier: Intended Audience :: Financial and Insurance Industry
Classifier: License :: OSI Approved :: MIT License
Classifier: Natural Language :: English
Classifier: Programming Language :: Python :: 3
Classifier: Programming Language :: Python :: 3 :: Only
Classifier: Programming Language :: Python :: 3.10
Classifier: Programming Language :: Python :: 3.7
Classifier: Programming Language :: Python :: 3.8
Classifier: Programming Language :: Python :: 3.9
Classifier: Topic :: Office/Business :: Financial :: Accounting
Classifier: Topic :: Utilities
Requires-Dist: dateparser (>=0.7)
Requires-Dist: logbook (>=1)
Requires-Dist: pandas (>=1.1.0,<1.2.0)
Requires-Dist: requests (>=2.21)
Requires-Dist: tables (>=3)
Requires-Dist: tqdm (>=4)
Project-URL: Repository, https://github.com/anson-vandoren/binance-downloader.git
